taxcalcindia/__init__.py
taxcalcindia/calculator.py
taxcalcindia/exceptions.py
taxcalcindia/models.py
taxcalcindia/slabs.py
taxcalcindia-0.1.3.dist-info/licenses/LICENSE
taxcalcindia-0.1.3.dist-info/METADATA
taxcalcindia-0.1.3.dist-info/WHEEL
taxcalcindia-0.1.3.dist-info/top_level.txt
taxcalcindia-0.1.3.dist-info/RECORD
