Metadata-Version: 2.4
Name: taxcalcindia
Version: 0.1.3
Summary: A package to calculate income tax for Indian taxpayers
Home-page: https://github.com/amrajacivil/taxcalcindia
Author: Arumugam Maharaja
Author-email: Arumugam Maharaja <raja1998civil@gmail.com>
License: MIT
Project-URL: Homepage, https://github.com/amrajacivil/taxcalcindia
Requires-Python: >=3.9
License-File: LICENSE
Dynamic: author
Dynamic: home-page
Dynamic: license-file
Dynamic: requires-python
